quantbullet/__init__.py
quantbullet/global_utils.py
quantbullet/log_config.py
quantbullet/model/__init__.py
quantbullet/model/anomaly.py
quantbullet/model/consts.py
quantbullet/model/last_value_estimator.py
quantbullet/model/linear_model.py
quantbullet/model/neighbors.py
quantbullet/model/time_weighted_xgboost.py
quantbullet/model_selection/__init__.py
quantbullet/model_selection/split.py
quantbullet/model_selection/validation.py
quantbullet/quantbullet.py
quantbullet/research/__init__.py
quantbullet/research/jump_model.py
quantbullet/research/mean_reversion.py
quantbullet/research/momentum.py
quantbullet/tsa/__init__.py
quantbullet/tsa/arima.py
quantbullet/utils/__init__.py
quantbullet/utils/backtest.py
quantbullet/utils/data.py
quantbullet/utils/helper.py
quantbullet/utils/plot.py
quantbullet/utils/validation.py
quantbullet-0.1.1.dist-info/LICENSE
quantbullet-0.1.1.dist-info/METADATA
quantbullet-0.1.1.dist-info/WHEEL
quantbullet-0.1.1.dist-info/RECORD
