Metadata-Version: 2.1
Name: quantbullet
Version: 0.1.1
Summary: Toolkit for swift quant analysis
License: MIT
Author: Yiming Zhang
Requires-Python: >=3.9
Classifier: License :: OSI Approved :: MIT License
Classifier: Programming Language :: Python :: 3
Classifier: Programming Language :: Python :: 3.9
Classifier: Programming Language :: Python :: 3.10
Classifier: Programming Language :: Python :: 3.11
Classifier: Programming Language :: Python :: 3.12
Requires-Dist: cvxpy (>=1.3.2,<2.0.0)
Requires-Dist: importlib-resources (>=6.1.0,<7.0.0)
Requires-Dist: matplotlib (>=3.7.3,<4.0.0)
Requires-Dist: optuna (>=3.4.0,<4.0.0)
Requires-Dist: pandas (>=2.1.0,<3.0.0)
Requires-Dist: scikit-learn (>=1.3.0,<2.0.0)
Requires-Dist: seaborn (>=0.13.0,<0.14.0)
Requires-Dist: statsmodels (>=0.14.0,<0.15.0)
Requires-Dist: tqdm (>=4.66.1,<5.0.0)
Requires-Dist: xgboost (>=2.0.2,<3.0.0)
